softfloatpy/__init__.py
softfloatpy/_core.cpython-311-x86_64-linux-gnu.so
softfloatpy/_core.pyi
softfloatpy/_version.py
softfloatpy/py.typed
softfloatpy-1.2.3.post1.dist-info/METADATA
softfloatpy-1.2.3.post1.dist-info/WHEEL
softfloatpy-1.2.3.post1.dist-info/top_level.txt
softfloatpy-1.2.3.post1.dist-info/RECORD
softfloatpy-1.2.3.post1.dist-info/licenses/LICENSE
