Metadata-Version: 2.4
Name: softfloatpy
Version: 1.2.3.post1
Summary: A Python binding of Berkeley SoftFloat
Home-page: https://github.com/arithy/softfloatpy
Author: Arihiro Yoshida
Author-email: software@arithy.org
License: MIT License
Requires-Python: <4,>=3.11
License-File: LICENSE
Provides-Extra: dev
Requires-Dist: pytest; extra == "dev"
Requires-Dist: mypy; extra == "dev"
Requires-Dist: flake8; extra == "dev"
Provides-Extra: doc
Requires-Dist: sphinx; extra == "doc"
Requires-Dist: sphinx-rtd-theme; extra == "doc"
Requires-Dist: myst-parser; extra == "doc"
Dynamic: license-file
